example_package/__init__.py
example_package/mathis.py
mathis1-0.0.1.dist-info/LICENSE
mathis1-0.0.1.dist-info/METADATA
mathis1-0.0.1.dist-info/WHEEL
mathis1-0.0.1.dist-info/top_level.txt
mathis1-0.0.1.dist-info/RECORD
