Metadata-Version: 2.1
Name: mathis1
Version: 0.0.1
Summary: A small example package
Home-page: https://github.com/mathismathis/mathis_auto_login
Author: mathis
Author-email: mathisit052@gmail.com
License: UNKNOWN
Project-URL: Bug Tracker, https://github.com/mathismathis/mathis_auto_login/issues
Platform: UNKNOWN
Classifier: Programming Language :: Python :: 3
Classifier: License :: OSI Approved :: MIT License
Classifier: Operating System :: OS Independent
Requires-Python: >=3.6
License-File: LICENSE
